{
  "timestamp": "2025-07-22 02:40:05.394060",
  "context": {
    "port_category": "web_secure",
    "port": 443,
    "service_fingerprint": "9a25b312",
    "service_length": 37,
    "tech_family": "cms",
    "tech": "wordpress",
    "os_family": null,
    "version": null,
    "has_headers": false
  },
  "result": {
    "score": 1.0,
    "explanation": {
      "exact_match": 1.0,
      "tech_category": 0.9,
      "port_context": 0.8999999999999999,
      "service_keywords": 0.5,
      "generic_fallback": 0.0
    },
    "wordlists": [
      "caddy-config.txt",
      "php-common.txt",
      "phpmyadmin-https.txt",
      "cms-common.txt",
      "ssl-paths.txt",
      "wp-plugins.txt",
      "caddy-paths.txt",
      "tls-endpoints.txt",
      "cms-plugins.txt",
      "web-content.txt",
      "cms-themes.txt",
      "dirs.txt",
      "common-https.txt",
      "common.txt",
      "wordpress-https.txt",
      "wp-themes.txt",
      "dirs-https.txt"
    ],
    "matched_rules": [
      "exact:wordpress:443",
      "tech_category:cms",
      "port:web_secure",
      "keyword:ssl"
    ],
    "fallback_used": false,
    "cache_key": "cms_web_secure_443_9a25b312",
    "confidence": "high",
    "entropy_score": 0.920147809149976,
    "diversification_applied": false,
    "frequency_adjustments": null,
    "synergy_bonuses": null
  },
  "outcome": null
}